sonyflake/__init__.py
sonyflake/about.py
sonyflake/py.typed
sonyflake/sonyflake.py
sonyflake_py-1.3.0.dist-info/LICENSE
sonyflake_py-1.3.0.dist-info/METADATA
sonyflake_py-1.3.0.dist-info/WHEEL
sonyflake_py-1.3.0.dist-info/top_level.txt
sonyflake_py-1.3.0.dist-info/RECORD
