Metadata-Version: 2.1
Name: sonyflake-py
Version: 1.3.0
Summary: A distributed unique ID generator inspired by Twitter's Snowflake.
Home-page: https://github.com/hjpotter92/sonyflake-py
Author: hjpotter92
Author-email: sonyflake-py@pypi.hjpotter92.email
License: UNKNOWN
Project-URL: Documentation, https://sonyflake-py.rtfd.io/
Project-URL: Code coverage, https://app.codecov.io/gh/hjpotter92/sonyflake-py
Project-URL: Builds history, https://travis-ci.com/hjpotter92/sonyflake-py
Project-URL: Changelog, https://sonyflake-py.rtfd.io/changelog
Platform: UNKNOWN
Classifier: Development Status :: 5 - Production/Stable
Classifier: Intended Audience :: Developers
Classifier: License :: OSI Approved :: MIT License
Classifier: Operating System :: OS Independent
Classifier: Programming Language :: Python :: 3
Classifier: Programming Language :: Python :: 3 :: Only
Classifier: Programming Language :: Python :: Implementation
Classifier: Topic :: Software Development :: Libraries :: Python Modules
Classifier: Topic :: System :: Distributed Computing
Requires-Python: >=3.6
